base/__init__.py
base/logger.py
program/__init__.py
program/__version__.py
program/main.py
excel_report_parser-0.1.0.dist-info/LICENSE
excel_report_parser-0.1.0.dist-info/METADATA
excel_report_parser-0.1.0.dist-info/WHEEL
excel_report_parser-0.1.0.dist-info/entry_points.txt
excel_report_parser-0.1.0.dist-info/top_level.txt
excel_report_parser-0.1.0.dist-info/RECORD
