Metadata-Version: 2.1
Name: excel-report-parser
Version: 0.1.0
Summary: Excel report file parser.
Home-page: https://github.com/me/null
Author: bing.feng
Author-email: bing.feng@example.com
License: MIT
Classifier: License :: OSI Approved :: MIT License
Classifier: Programming Language :: Python
Classifier: Programming Language :: Python :: 3
Classifier: Programming Language :: Python :: 3.6
Classifier: Programming Language :: Python :: Implementation :: CPython
Classifier: Programming Language :: Python :: Implementation :: PyPy
Requires-Python: >=3.6.0
License-File: LICENSE
